Workbook
Name solver_est: 1
Name solver_lin: 2
Name solver_nwt: 1

Sheet Summary
A1: Budget model: which channels deserve next quarter's marketing budget?
A2: FinTech Customer Acquisition and Profitability Analysis. Synthetic data, extract date 2026-09-30. All numbers in EUR.
A4: Headline question
A5: Which acquisition channels bring profitable customers, and how should next quarter's budget be reallocated?
A7: Recommended allocation (Solver result, base case)
A8: Channel | B8: Baseline spend (EUR) | C8: Recommended spend (EUR) | D8: Change | E8: Recommended, rounded to 100 (EUR) | F8: Risk-adjusted LTV per customer (EUR) | G8: CAC (EUR)
A9: =Optimizer!A5 -> affiliate | B9: =Optimizer!B5 -> 3116.48 | C9: =Optimizer!E5 -> 1558.24 | D9: =Optimizer!F5 -> -0.5 | E9: =ROUND(C9/100,0)*100 -> 1600 | F9: =VLOOKUP(A9,Unit_Economics!$A$5:$T$9,17,FALSE) -> -490.95 | G9: =VLOOKUP(A9,Unit_Economics!$A$5:$T$9,7,FALSE) -> 32.030248
A10: =Optimizer!A6 -> paid_search | B10: =Optimizer!B6 -> 5374.79 | C10: =Optimizer!E6 -> 2687.395 | D10: =Optimizer!F6 -> -0.5 | E10: =ROUND(C10/100,0)*100 -> 2700 | F10: =VLOOKUP(A10,Unit_Economics!$A$5:$T$9,17,FALSE) -> -31.96 | G10: =VLOOKUP(A10,Unit_Economics!$A$5:$T$9,7,FALSE) -> 32.942524
A11: =Optimizer!A7 -> paid_social | B11: =Optimizer!B7 -> 19030.08 | C11: =Optimizer!E7 -> 9515.04 | D11: =Optimizer!F7 -> -0.5 | E11: =ROUND(C11/100,0)*100 -> 9500 | F11: =VLOOKUP(A11,Unit_Economics!$A$5:$T$9,17,FALSE) -> -54.03 | G11: =VLOOKUP(A11,Unit_Economics!$A$5:$T$9,7,FALSE) -> 65.59049
A12: =Optimizer!A8 -> referral | B12: =Optimizer!B8 -> 1081.34 | C12: =Optimizer!E8 -> 1297.608 | D12: =Optimizer!F8 -> 0.2 | E12: =ROUND(C12/100,0)*100 -> 1300 | F12: =VLOOKUP(A12,Unit_Economics!$A$5:$T$9,17,FALSE) -> 54.49 | G12: =VLOOKUP(A12,Unit_Economics!$A$5:$T$9,7,FALSE) -> 12.468485
A13: Total | B13: =Optimizer!B9 -> 28602.69 | C13: =Optimizer!E9 -> 15058.283 | D13: =Optimizer!F9 -> -0.47353613 | E13: =SUM(E9:E12) -> 15100
A15: Result
A16: Net profit at baseline spend (EUR per quarter) | B16: =Optimizer!B13 -> -97563.641
A17: Net profit at recommended spend (EUR per quarter) | B17: =Optimizer!B14 -> -56843.21
A18: Improvement (EUR per quarter) | B18: =Optimizer!B15 -> 40720.431
A20: What the model says (at the delivered inputs)
A21: 1. After credit losses, only referral earns money per customer. Affiliate looks best before losses but loses the most per customer, because its borrowers default far more often.
A22: 2. The best allocation puts affiliate, paid search and paid social at their lower limit (50 percent of baseline) and referral at its upper limit (120 percent). The model never wants more spend in a channel whose customers lose money.
A23: 3. Moving the money this way improves the quarter, but the net result is still negative. The remaining loss comes from loan losses, so the biggest lever is credit policy, not channel mix.
A24: 4. Paid social was inflated by one campaign (SO_Summer_Reach_2026, about 24 percent of its spend, 365 EUR per customer against a channel median of 62). Cutting it costs few customers.
A25: 5. The three channels stay at their lower limit in every scenario (budget plus or minus 20 percent, credit losses plus or minus 25 percent, interest after month 12 counted). See the sheet Scenarios.
A27: Limits: synthetic data and assumed default behaviour; the curves are rough (see R squared on sheet Curves); the sentences above describe the delivered inputs and do not update by themselves. More in sheet Notes.
A29: How to read the colours
A30: Blue on yellow: an input you can change
A31: Green: a link to another sheet
A32: Black: a formula
A33: Green fill: a key result
A35: Sheets: Assumptions (inputs) > Unit_Economics (CAC, LTV, payback) > Curves (spend to customers) > Optimizer (Solver) > Scenarios > Pivot_Tables. Data_ sheets hold the SQL view results.

Sheet Assumptions
A1: Assumptions
A2: Blue cells on yellow are inputs. Everything else in the workbook is calculated from them and from the SQL data sheets.
A4: Input | B4: Value | C4: Unit | D4: Where it comes from / what it does
A5: KYC cost per identity check | B5: 2.5 | C5: EUR | D5: assumptions table (kyc_cost_per_check). Part of CAC.
A6: Months in the planning quarter | B6: 3 | C6: months | D6: Converts the monthly response curve into a quarterly number.
A7: Budget multiplier (scenario lever) | B7: 1 | C7: x | D7: 1.0 = the baseline budget (July to September 2026 spend). 0.8 = minus 20 percent.
A8: Credit loss multiplier (scenario lever) | B8: 1 | C8: x | D8: 1.0 = observed credit losses. 1.25 = default losses 25 percent higher.
A9: Lower limit per channel | B9: 0.5 | C9: % of baseline | D9: Project decision: each channel keeps at least 50 percent of its baseline spend.
A10: Upper limit per channel | B10: 1.5 | C10: % of baseline | D10: Project decision: each channel gets at most 150 percent of its baseline spend.
A11: Upper limit for referral | B11: 1.2 | C11: % of baseline | D11: Project decision: referral volume is limited by the existing customer base.
A12: Leave the SO_Summer_Reach months (June to September 2026) out of the paid social curve | B12: 1 | C12: 1 = yes, 0 = no | D12: The wasteful campaign ran in those months and distorts the curve. 1 fits paid social on the first 20 months.
A13: Weak fit threshold (R squared) | B13: 0.3 | C13: R squared | D13: Curves below this are flagged as weak fits.
A15: Interest earned after month 12 (not in the 12-month LTV)
A16: Channel | B16: Value per customer (EUR) | C16: Unit | D16: Note
A17: affiliate | B17: 0 | C17: EUR per customer | D17: Default 0, as defined in the project. Measured on the 12-month cohort: 69.10 EUR per customer. Enter it to count interest after month 12.
A18: organic | B18: 0 | C18: EUR per customer | D18: Default 0, as defined in the project. Measured on the 12-month cohort: 43.51 EUR per customer. Enter it to count interest after month 12.
A19: paid_search | B19: 0 | C19: EUR per customer | D19: Default 0, as defined in the project. Measured on the 12-month cohort: 53.16 EUR per customer. Enter it to count interest after month 12.
A20: paid_social | B20: 0 | C20: EUR per customer | D20: Default 0, as defined in the project. Measured on the 12-month cohort: 48.08 EUR per customer. Enter it to count interest after month 12.
A21: referral | B21: 0 | C21: EUR per customer | D21: Default 0, as defined in the project. Measured on the 12-month cohort: 43.60 EUR per customer. Enter it to count interest after month 12.
A23: Fixed project definitions (not inputs): CAC = (ad spend + KYC cost) / funded customers; LTV is the observed 12-month margin; risk-adjusted LTV = LTV minus credit loss per customer; the response curve is customers = a x spend^b.

Sheet Unit_Economics
A1: Unit economics by channel
A2: CAC, LTV, payback and ROAS recomputed from the SQL data and the assumptions. Organic has no ad spend, so it has no CAC.
A4: Channel | B4: Has ad spend (1/0) | C4: Ad spend (EUR) | D4: Funded customers | E4: KYC decisions | F4: KYC cost (EUR) | G4: CAC (EUR) | H4: Ad-only CAC (EUR) | I4: Customers in 12-month cohort | J4: LTV 12 months, before credit loss (EUR) | K4: Revenue 12 months (EUR) | L4: LTV / CAC | M4: ROAS | N4: Payback month | O4: Credit loss per customer (EUR) | P4: Interest after month 12 (EUR) | Q4: Risk-adjusted LTV (EUR) | R4: Risk-adjusted LTV / CAC | S4: KYC cost per funded customer (EUR) | T4: Net value per customer (EUR)
A5: =Data_Scorecard!A2 -> affiliate | B5: =IF(Data_Scorecard!B2>0,1,0) -> 1 | C5: =Data_Scorecard!B2 -> 23677.59 | D5: =Data_Scorecard!C2 -> 846 | E5: =Data_Scorecard!D2 -> 1368 | F5: =E5*Assumptions!$B$5 -> 3420 | G5: =IF(B5=1,(C5+F5)/D5,"n/a") -> 32.030248 | H5: =IF(B5=1,C5/D5,"n/a") -> 27.987695 | I5: =Data_Scorecard!H2 -> 382 | J5: =Data_Scorecard!I2 -> 251.54 | K5: =Data_Scorecard!J2 -> 321.21 | L5: =IF(B5=1,J5/G5,"n/a") -> 7.8532017 | M5: =IF(B5=1,K5/H5,"n/a") -> 11.476829 | N5: =IF(B5=1,IF(COUNTIF(B14:M14,"<"&G5)=12,"not paid back",COUNTIF(B14:M14,"<"&G5)+1),"n/a") -> 3 | O5: =Data_Scorecard!O2*Assumptions!$B$8 -> 742.49 | P5: =Assumptions!B17 -> 0 | Q5: =J5+P5-O5 -> -490.95 | R5: =IF(B5=1,Q5/G5,"n/a") -> -15.327699 | S5: =F5/D5 -> 4.0425532 | T5: =Q5-S5 -> -494.99255
A6: =Data_Scorecard!A3 -> organic | B6: =IF(Data_Scorecard!B3>0,1,0) -> 0 | C6: =Data_Scorecard!B3 -> 0 | D6: =Data_Scorecard!C3 -> 1401 | E6: =Data_Scorecard!D3 -> 1831 | F6: =E6*Assumptions!$B$5 -> 4577.5 | G6: =IF(B6=1,(C6+F6)/D6,"n/a") -> n/a | H6: =IF(B6=1,C6/D6,"n/a") -> n/a | I6: =Data_Scorecard!H3 -> 650 | J6: =Data_Scorecard!I3 -> 167.97 | K6: =Data_Scorecard!J3 -> 217.02 | L6: =IF(B6=1,J6/G6,"n/a") -> n/a | M6: =IF(B6=1,K6/H6,"n/a") -> n/a | N6: =IF(B6=1,IF(COUNTIF(B15:M15,"<"&G6)=12,"not paid back",COUNTIF(B15:M15,"<"&G6)+1),"n/a") -> n/a | O6: =Data_Scorecard!O3*Assumptions!$B$8 -> 196.21 | P6: =Assumptions!B18 -> 0 | Q6: =J6+P6-O6 -> -28.24 | R6: =IF(B6=1,Q6/G6,"n/a") -> n/a | S6: =F6/D6 -> 3.2673091 | T6: =Q6-S6 -> -31.507309
A7: =Data_Scorecard!A4 -> paid_search | B7: =IF(Data_Scorecard!B4>0,1,0) -> 1 | C7: =Data_Scorecard!B4 -> 45681.2 | D7: =Data_Scorecard!C4 -> 1545 | E7: =Data_Scorecard!D4 -> 2086 | F7: =E7*Assumptions!$B$5 -> 5215 | G7: =IF(B7=1,(C7+F7)/D7,"n/a") -> 32.942524 | H7: =IF(B7=1,C7/D7,"n/a") -> 29.56712 | I7: =Data_Scorecard!H4 -> 719 | J7: =Data_Scorecard!I4 -> 185.36 | K7: =Data_Scorecard!J4 -> 237.31 | L7: =IF(B7=1,J7/G7,"n/a") -> 5.6267698 | M7: =IF(B7=1,K7/H7,"n/a") -> 8.0261453 | N7: =IF(B7=1,IF(COUNTIF(B16:M16,"<"&G7)=12,"not paid back",COUNTIF(B16:M16,"<"&G7)+1),"n/a") -> 4 | O7: =Data_Scorecard!O4*Assumptions!$B$8 -> 217.32 | P7: =Assumptions!B19 -> 0 | Q7: =J7+P7-O7 -> -31.96 | R7: =IF(B7=1,Q7/G7,"n/a") -> -0.97017459 | S7: =F7/D7 -> 3.3754045 | T7: =Q7-S7 -> -35.335405
A8: =Data_Scorecard!A5 -> paid_social | B8: =IF(Data_Scorecard!B5>0,1,0) -> 1 | C8: =Data_Scorecard!B5 -> 73973.35 | D8: =Data_Scorecard!C5 -> 1225 | E8: =Data_Scorecard!D5 -> 2550 | F8: =E8*Assumptions!$B$5 -> 6375 | G8: =IF(B8=1,(C8+F8)/D8,"n/a") -> 65.59049 | H8: =IF(B8=1,C8/D8,"n/a") -> 60.386408 | I8: =Data_Scorecard!H5 -> 562 | J8: =Data_Scorecard!I5 -> 171.28 | K8: =Data_Scorecard!J5 -> 216.32 | L8: =IF(B8=1,J8/G8,"n/a") -> 2.6113542 | M8: =IF(B8=1,K8/H8,"n/a") -> 3.5822631 | N8: =IF(B8=1,IF(COUNTIF(B17:M17,"<"&G8)=12,"not paid back",COUNTIF(B17:M17,"<"&G8)+1),"n/a") -> 6 | O8: =Data_Scorecard!O5*Assumptions!$B$8 -> 225.31 | P8: =Assumptions!B20 -> 0 | Q8: =J8+P8-O8 -> -54.03 | R8: =IF(B8=1,Q8/G8,"n/a") -> -0.82374747 | S8: =F8/D8 -> 5.2040816 | T8: =Q8-S8 -> -59.234082
A9: =Data_Scorecard!A6 -> referral | B9: =IF(Data_Scorecard!B6>0,1,0) -> 1 | C9: =Data_Scorecard!B6 -> 8718.79 | D9: =Data_Scorecard!C6 -> 911 | E9: =Data_Scorecard!D6 -> 1056 | F9: =E9*Assumptions!$B$5 -> 2640 | G9: =IF(B9=1,(C9+F9)/D9,"n/a") -> 12.468485 | H9: =IF(B9=1,C9/D9,"n/a") -> 9.5705708 | I9: =Data_Scorecard!H6 -> 467 | J9: =Data_Scorecard!I6 -> 165.36 | K9: =Data_Scorecard!J6 -> 217.06 | L9: =IF(B9=1,J9/G9,"n/a") -> 13.262237 | M9: =IF(B9=1,K9/H9,"n/a") -> 22.679943 | N9: =IF(B9=1,IF(COUNTIF(B18:M18,"<"&G9)=12,"not paid back",COUNTIF(B18:M18,"<"&G9)+1),"n/a") -> 2 | O9: =Data_Scorecard!O6*Assumptions!$B$8 -> 110.87 | P9: =Assumptions!B21 -> 0 | Q9: =J9+P9-O9 -> 54.49 | R9: =IF(B9=1,Q9/G9,"n/a") -> 4.3702181 | S9: =F9/D9 -> 2.8979144 | T9: =Q9-S9 -> 51.592086
A11: Reading: LTV is what a customer earns in 12 months. Risk-adjusted LTV subtracts the credit loss on that customer's loans. Net value per customer also subtracts the KYC cost; it is the value the optimizer uses.
A12: Cumulative margin per customer by month (data for the payback chart). A channel pays back in the first month its line reaches its CAC.
A13: Channel | B13: 1 | C13: 2 | D13: 3 | E13: 4 | F13: 5 | G13: 6 | H13: 7 | I13: 8 | J13: 9 | K13: 10 | L13: 11 | M13: 12
A14: =A5 -> affiliate | B14: =SUMIFS(Data_Curve!$D$2:$D$61,Data_Curve!$A$2:$A$61,$A14,Data_Curve!$B$2:$B$61,B$13) -> 2.4089 | C14: =SUMIFS(Data_Curve!$D$2:$D$61,Data_Curve!$A$2:$A$61,$A14,Data_Curve!$B$2:$B$61,C$13) -> 17.5263 | D14: =SUMIFS(Data_Curve!$D$2:$D$61,Data_Curve!$A$2:$A$61,$A14,Data_Curve!$B$2:$B$61,D$13) -> 42.817 | E14: =SUMIFS(Data_Curve!$D$2:$D$61,Data_Curve!$A$2:$A$61,$A14,Data_Curve!$B$2:$B$61,E$13) -> 65.3812 | F14: =SUMIFS(Data_Curve!$D$2:$D$61,Data_Curve!$A$2:$A$61,$A14,Data_Curve!$B$2:$B$61,F$13) -> 98.8193 | G14: =SUMIFS(Data_Curve!$D$2:$D$61,Data_Curve!$A$2:$A$61,$A14,Data_Curve!$B$2:$B$61,G$13) -> 131.4079 | H14: =SUMIFS(Data_Curve!$D$2:$D$61,Data_Curve!$A$2:$A$61,$A14,Data_Curve!$B$2:$B$61,H$13) -> 165.1691 | I14: =SUMIFS(Data_Curve!$D$2:$D$61,Data_Curve!$A$2:$A$61,$A14,Data_Curve!$B$2:$B$61,I$13) -> 189.4622 | ... M14: =SUMIFS(Data_Curve!$D$2:$D$61,Data_Curve!$A$2:$A$61,$A14,Data_Curve!$B$2:$B$61,M$13) -> 251.5416
A15: =A6 -> organic | B15: =SUMIFS(Data_Curve!$D$2:$D$61,Data_Curve!$A$2:$A$61,$A15,Data_Curve!$B$2:$B$61,B$13) -> 1.2566 | C15: =SUMIFS(Data_Curve!$D$2:$D$61,Data_Curve!$A$2:$A$61,$A15,Data_Curve!$B$2:$B$61,C$13) -> 13.9257 | D15: =SUMIFS(Data_Curve!$D$2:$D$61,Data_Curve!$A$2:$A$61,$A15,Data_Curve!$B$2:$B$61,D$13) -> 30.1717 | E15: =SUMIFS(Data_Curve!$D$2:$D$61,Data_Curve!$A$2:$A$61,$A15,Data_Curve!$B$2:$B$61,E$13) -> 47.6578 | F15: =SUMIFS(Data_Curve!$D$2:$D$61,Data_Curve!$A$2:$A$61,$A15,Data_Curve!$B$2:$B$61,F$13) -> 67.6187 | G15: =SUMIFS(Data_Curve!$D$2:$D$61,Data_Curve!$A$2:$A$61,$A15,Data_Curve!$B$2:$B$61,G$13) -> 89.3921 | H15: =SUMIFS(Data_Curve!$D$2:$D$61,Data_Curve!$A$2:$A$61,$A15,Data_Curve!$B$2:$B$61,H$13) -> 113.1514 | I15: =SUMIFS(Data_Curve!$D$2:$D$61,Data_Curve!$A$2:$A$61,$A15,Data_Curve!$B$2:$B$61,I$13) -> 128.3168 | ... M15: =SUMIFS(Data_Curve!$D$2:$D$61,Data_Curve!$A$2:$A$61,$A15,Data_Curve!$B$2:$B$61,M$13) -> 167.97
A16: =A7 -> paid_search | B16: =SUMIFS(Data_Curve!$D$2:$D$61,Data_Curve!$A$2:$A$61,$A16,Data_Curve!$B$2:$B$61,B$13) -> 2.528 | C16: =SUMIFS(Data_Curve!$D$2:$D$61,Data_Curve!$A$2:$A$61,$A16,Data_Curve!$B$2:$B$61,C$13) -> 13.915 | D16: =SUMIFS(Data_Curve!$D$2:$D$61,Data_Curve!$A$2:$A$61,$A16,Data_Curve!$B$2:$B$61,D$13) -> 29.5704 | E16: =SUMIFS(Data_Curve!$D$2:$D$61,Data_Curve!$A$2:$A$61,$A16,Data_Curve!$B$2:$B$61,E$13) -> 47.8712 | F16: =SUMIFS(Data_Curve!$D$2:$D$61,Data_Curve!$A$2:$A$61,$A16,Data_Curve!$B$2:$B$61,F$13) -> 69.491 | G16: =SUMIFS(Data_Curve!$D$2:$D$61,Data_Curve!$A$2:$A$61,$A16,Data_Curve!$B$2:$B$61,G$13) -> 95.6318 | H16: =SUMIFS(Data_Curve!$D$2:$D$61,Data_Curve!$A$2:$A$61,$A16,Data_Curve!$B$2:$B$61,H$13) -> 121.1137 | I16: =SUMIFS(Data_Curve!$D$2:$D$61,Data_Curve!$A$2:$A$61,$A16,Data_Curve!$B$2:$B$61,I$13) -> 135.1869 | ... M16: =SUMIFS(Data_Curve!$D$2:$D$61,Data_Curve!$A$2:$A$61,$A16,Data_Curve!$B$2:$B$61,M$13) -> 185.3614
A17: =A8 -> paid_social | B17: =SUMIFS(Data_Curve!$D$2:$D$61,Data_Curve!$A$2:$A$61,$A17,Data_Curve!$B$2:$B$61,B$13) -> 1.4054 | C17: =SUMIFS(Data_Curve!$D$2:$D$61,Data_Curve!$A$2:$A$61,$A17,Data_Curve!$B$2:$B$61,C$13) -> 11.9423 | D17: =SUMIFS(Data_Curve!$D$2:$D$61,Data_Curve!$A$2:$A$61,$A17,Data_Curve!$B$2:$B$61,D$13) -> 27.5278 | E17: =SUMIFS(Data_Curve!$D$2:$D$61,Data_Curve!$A$2:$A$61,$A17,Data_Curve!$B$2:$B$61,E$13) -> 43.983 | F17: =SUMIFS(Data_Curve!$D$2:$D$61,Data_Curve!$A$2:$A$61,$A17,Data_Curve!$B$2:$B$61,F$13) -> 62.2427 | G17: =SUMIFS(Data_Curve!$D$2:$D$61,Data_Curve!$A$2:$A$61,$A17,Data_Curve!$B$2:$B$61,G$13) -> 83.5843 | H17: =SUMIFS(Data_Curve!$D$2:$D$61,Data_Curve!$A$2:$A$61,$A17,Data_Curve!$B$2:$B$61,H$13) -> 106.1914 | I17: =SUMIFS(Data_Curve!$D$2:$D$61,Data_Curve!$A$2:$A$61,$A17,Data_Curve!$B$2:$B$61,I$13) -> 124.4682 | ... M17: =SUMIFS(Data_Curve!$D$2:$D$61,Data_Curve!$A$2:$A$61,$A17,Data_Curve!$B$2:$B$61,M$13) -> 171.2796
A18: =A9 -> referral | B18: =SUMIFS(Data_Curve!$D$2:$D$61,Data_Curve!$A$2:$A$61,$A18,Data_Curve!$B$2:$B$61,B$13) -> 0.9876 | C18: =SUMIFS(Data_Curve!$D$2:$D$61,Data_Curve!$A$2:$A$61,$A18,Data_Curve!$B$2:$B$61,C$13) -> 14.2468 | D18: =SUMIFS(Data_Curve!$D$2:$D$61,Data_Curve!$A$2:$A$61,$A18,Data_Curve!$B$2:$B$61,D$13) -> 29.1244 | E18: =SUMIFS(Data_Curve!$D$2:$D$61,Data_Curve!$A$2:$A$61,$A18,Data_Curve!$B$2:$B$61,E$13) -> 45.638 | F18: =SUMIFS(Data_Curve!$D$2:$D$61,Data_Curve!$A$2:$A$61,$A18,Data_Curve!$B$2:$B$61,F$13) -> 60.3247 | G18: =SUMIFS(Data_Curve!$D$2:$D$61,Data_Curve!$A$2:$A$61,$A18,Data_Curve!$B$2:$B$61,G$13) -> 82.4092 | H18: =SUMIFS(Data_Curve!$D$2:$D$61,Data_Curve!$A$2:$A$61,$A18,Data_Curve!$B$2:$B$61,H$13) -> 104.3729 | I18: =SUMIFS(Data_Curve!$D$2:$D$61,Data_Curve!$A$2:$A$61,$A18,Data_Curve!$B$2:$B$61,I$13) -> 119.5962 | ... M18: =SUMIFS(Data_Curve!$D$2:$D$61,Data_Curve!$A$2:$A$61,$A18,Data_Curve!$B$2:$B$61,M$13) -> 165.3593

Sheet Curves
A1: Response curves: customers = a x spend^b
A2: Fitted on the log of monthly spend and monthly credited customers, 24 monthly points per channel (20 for paid social when the Summer Reach months are left out).
A4: Channel | B4: Points used | C4: b (slope) | D4: ln(a) (intercept) | E4: a | F4: R squared | G4: Fit quality | H4: Baseline monthly spend (EUR) | I4: Curve: customers per month at baseline spend | J4: Actual average customers per month, Jul to Sep 2026
A5: affiliate | B5: =COUNT(Data_Monthly!$G$2:$G$25) -> 24 | C5: =INDEX(LINEST(Data_Monthly!$G$2:$G$25,Data_Monthly!$F$2:$F$25),1,1) -> 0.64074556 | D5: =INDEX(LINEST(Data_Monthly!$G$2:$G$25,Data_Monthly!$F$2:$F$25),1,2) -> -0.86981811 | E5: =EXP(D5) -> 0.41902776 | F5: =RSQ(Data_Monthly!$G$2:$G$25,Data_Monthly!$F$2:$F$25) -> 0.34174202 | G5: =IF(F5<Assumptions!$B$13,"weak fit","ok") -> ok | H5: =SUMIFS(Data_Monthly!$C$2:$C$97,Data_Monthly!$A$2:$A$97,A5,Data_Monthly!$E$2:$E$97,1)/Assumptions!$B$6 -> 1038.8267 | I5: =E5*H5^C5 -> 35.898755 | J5: =AVERAGEIFS(Data_Monthly!$D$2:$D$97,Data_Monthly!$A$2:$A$97,A5,Data_Monthly!$E$2:$E$97,1) -> 38.513333
A6: paid_search | B6: =COUNT(Data_Monthly!$G$26:$G$49) -> 24 | C6: =INDEX(LINEST(Data_Monthly!$G$26:$G$49,Data_Monthly!$F$26:$F$49),1,1) -> 0.69134009 | D6: =INDEX(LINEST(Data_Monthly!$G$26:$G$49,Data_Monthly!$F$26:$F$49),1,2) -> -0.85181066 | E6: =EXP(D6) -> 0.42664173 | F6: =RSQ(Data_Monthly!$G$26:$G$49,Data_Monthly!$F$26:$F$49) -> 0.70039214 | G6: =IF(F6<Assumptions!$B$13,"weak fit","ok") -> ok | H6: =SUMIFS(Data_Monthly!$C$2:$C$97,Data_Monthly!$A$2:$A$97,A6,Data_Monthly!$E$2:$E$97,1)/Assumptions!$B$6 -> 1791.5967 | I6: =E6*H6^C6 -> 75.710957 | J6: =AVERAGEIFS(Data_Monthly!$D$2:$D$97,Data_Monthly!$A$2:$A$97,A6,Data_Monthly!$E$2:$E$97,1) -> 74.043333
A7: paid_social | B7: =IF(Assumptions!$B$12=1,COUNT(Data_Monthly!$G$50:$G$69),COUNT(Data_Monthly!$G$50:$G$73)) -> 20 | C7: =IF(Assumptions!$B$12=1,INDEX(LINEST(Data_Monthly!$G$50:$G$69,Data_Monthly!$F$50:$F$69),1,1),INDEX(LINEST(Data_Monthly!$G$50:$G$73,Data_Monthly!$F$50:$F$73),1,1)) -> 0.61630237 | D7: =IF(Assumptions!$B$12=1,INDEX(LINEST(Data_Monthly!$G$50:$G$69,Data_Monthly!$F$50:$F$69),1,2),INDEX(LINEST(Data_Monthly!$G$50:$G$73,Data_Monthly!$F$50:$F$73),1,2)) -> -1.0916051 | E7: =EXP(D7) -> 0.33567726 | F7: =IF(Assumptions!$B$12=1,RSQ(Data_Monthly!$G$50:$G$69,Data_Monthly!$F$50:$F$69),RSQ(Data_Monthly!$G$50:$G$73,Data_Monthly!$F$50:$F$73)) -> 0.54617888 | G7: =IF(F7<Assumptions!$B$13,"weak fit","ok") -> ok | H7: =SUMIFS(Data_Monthly!$C$2:$C$97,Data_Monthly!$A$2:$A$97,A7,Data_Monthly!$E$2:$E$97,1)/Assumptions!$B$6 -> 6343.36 | I7: =E7*H7^C7 -> 74.011695 | J7: =AVERAGEIFS(Data_Monthly!$D$2:$D$97,Data_Monthly!$A$2:$A$97,A7,Data_Monthly!$E$2:$E$97,1) -> 40.143333
A8: referral | B8: =COUNT(Data_Monthly!$G$74:$G$97) -> 24 | C8: =INDEX(LINEST(Data_Monthly!$G$74:$G$97,Data_Monthly!$F$74:$F$97),1,1) -> 0.41142656 | D8: =INDEX(LINEST(Data_Monthly!$G$74:$G$97,Data_Monthly!$F$74:$F$97),1,2) -> 1.1529884 | E8: =EXP(D8) -> 3.1676448 | F8: =RSQ(Data_Monthly!$G$74:$G$97,Data_Monthly!$F$74:$F$97) -> 0.251005 | G8: =IF(F8<Assumptions!$B$13,"weak fit","ok") -> weak fit | H8: =SUMIFS(Data_Monthly!$C$2:$C$97,Data_Monthly!$A$2:$A$97,A8,Data_Monthly!$E$2:$E$97,1)/Assumptions!$B$6 -> 360.44667 | I8: =E8*H8^C8 -> 35.701691 | J8: =AVERAGEIFS(Data_Monthly!$D$2:$D$97,Data_Monthly!$A$2:$A$97,A8,Data_Monthly!$E$2:$E$97,1) -> 36.38
A10: How to read it: b below 1 means diminishing returns (doubling the spend gives less than double the customers). A low R squared means monthly spend explains little of the monthly customers, so treat that curve as rough. Compare the last two columns: if the curve gives far more customers than were actually won, the baseline spend was inefficient (this is the case for paid social).

Sheet Optimizer
A1: Budget optimizer
A2: Maximise net profit (customers x net value per customer - ad spend) by choosing the spend per channel. Run Solver (Data > Solver): the settings are already filled in.
A4: Channel | B4: Baseline spend, Jul to Sep 2026 (EUR) | C4: Lower limit (EUR) | D4: Upper limit (EUR) | E4: Recommended spend (EUR) <- Solver changes these | F4: Change vs baseline | G4: Customers at baseline spend | H4: Customers at recommended spend | I4: Net value per customer (EUR) | J4: Value of customers, baseline (EUR) | K4: Value of customers, recommended (EUR)
A5: affiliate | B5: =SUMIFS(Data_Monthly!$C$2:$C$97,Data_Monthly!$A$2:$A$97,A5,Data_Monthly!$E$2:$E$97,1) -> 3116.48 | C5: =B5*Assumptions!$B$9 -> 1558.24 | D5: =B5*IF(A5="referral",Assumptions!$B$11,Assumptions!$B$10) -> 4674.72 | E5: 1558.24 | F5: =E5/B5-1 -> -0.5 | G5: =Assumptions!$B$6*Curves!E5*(B5/Assumptions!$B$6)^Curves!C5 -> 107.69626 | H5: =Assumptions!$B$6*Curves!E5*(E5/Assumptions!$B$6)^Curves!C5 -> 69.074382 | I5: =VLOOKUP(A5,Unit_Economics!$A$5:$T$9,20,FALSE) -> -494.99255 | J5: =G5*I5 -> -53308.849 | K5: =H5*I5 -> -34191.305
A6: paid_search | B6: =SUMIFS(Data_Monthly!$C$2:$C$97,Data_Monthly!$A$2:$A$97,A6,Data_Monthly!$E$2:$E$97,1) -> 5374.79 | C6: =B6*Assumptions!$B$9 -> 2687.395 | D6: =B6*IF(A6="referral",Assumptions!$B$11,Assumptions!$B$10) -> 8062.185 | E6: 2687.395 | F6: =E6/B6-1 -> -0.5 | G6: =Assumptions!$B$6*Curves!E6*(B6/Assumptions!$B$6)^Curves!C6 -> 227.13287 | H6: =Assumptions!$B$6*Curves!E6*(E6/Assumptions!$B$6)^Curves!C6 -> 140.65847 | I6: =VLOOKUP(A6,Unit_Economics!$A$5:$T$9,20,FALSE) -> -35.335405 | J6: =G6*I6 -> -8025.8319 | K6: =H6*I6 -> -4970.2239
A7: paid_social | B7: =SUMIFS(Data_Monthly!$C$2:$C$97,Data_Monthly!$A$2:$A$97,A7,Data_Monthly!$E$2:$E$97,1) -> 19030.08 | C7: =B7*Assumptions!$B$9 -> 9515.04 | D7: =B7*IF(A7="referral",Assumptions!$B$11,Assumptions!$B$10) -> 28545.12 | E7: 9515.04 | F7: =E7/B7-1 -> -0.5 | G7: =Assumptions!$B$6*Curves!E7*(B7/Assumptions!$B$6)^Curves!C7 -> 222.03508 | H7: =Assumptions!$B$6*Curves!E7*(E7/Assumptions!$B$6)^Curves!C7 -> 144.84253 | I7: =VLOOKUP(A7,Unit_Economics!$A$5:$T$9,20,FALSE) -> -59.234082 | J7: =G7*I7 -> -13152.044 | K7: =H7*I7 -> -8579.6143
A8: referral | B8: =SUMIFS(Data_Monthly!$C$2:$C$97,Data_Monthly!$A$2:$A$97,A8,Data_Monthly!$E$2:$E$97,1) -> 1081.34 | C8: =B8*Assumptions!$B$9 -> 540.67 | D8: =B8*IF(A8="referral",Assumptions!$B$11,Assumptions!$B$10) -> 1297.608 | E8: 1297.608 | F8: =E8/B8-1 -> 0.2 | G8: =Assumptions!$B$6*Curves!E8*(B8/Assumptions!$B$6)^Curves!C8 -> 107.10507 | H8: =Assumptions!$B$6*Curves!E8*(E8/Assumptions!$B$6)^Curves!C8 -> 115.44824 | I8: =VLOOKUP(A8,Unit_Economics!$A$5:$T$9,20,FALSE) -> 51.592086 | J8: =G8*I8 -> 5525.7741 | K8: =H8*I8 -> 5956.2154
A9: Total | B9: =SUM(B5:B8) -> 28602.69 | E9: =SUM(E5:E8) -> 15058.283 | F9: =E9/B9-1 -> -0.47353613 | G9: =SUM(G5:G8) -> 663.96929 | H9: =SUM(H5:H8) -> 470.02362 | J9: =SUM(J5:J8) -> -68960.951 | K9: =SUM(K5:K8) -> -41784.927
A11: Budget ceiling (EUR) | B11: =B9*Assumptions!B7 -> 28602.69
A12: Total recommended spend (EUR) | B12: =E9 -> 15058.283
A13: Net profit at baseline spend (EUR) | B13: =J9-B9 -> -97563.641
A14: Net profit at recommended spend (EUR) <- Solver maximises this | B14: =K9-E9 -> -56843.21
A15: Uplift: recommended minus baseline (EUR) | B15: =B14-B13 -> 40720.431
A16: Spend within the budget ceiling? | B16: =IF(E9<=B11+0.005,"OK","OVER BUDGET") -> OK
A17: All channels inside their limits? | B17: =IF(SUMPRODUCT((E5:E8<C5:C8-0.005)+(E5:E8>D5:D8+0.005))=0,"OK","OUTSIDE LIMITS") -> OK
A19: Solver settings (already stored in this sheet): objective $B$14, maximise; changing cells $E$5:$E$8; constraints: $E$5:$E$8 >= $C$5:$C$8, $E$5:$E$8 <= $D$5:$D$8, $E$9 <= $B$11; method GRG Nonlinear; make unconstrained variables non-negative. If you change an assumption, run Solver again. The delivered values are the Solver result for the base case.

Sheet Scenarios
A1: Scenarios
A2: Each row is the optimum for one scenario (pasted values). To reproduce one, change the matching lever in Assumptions and run Solver on the Optimizer sheet.
A4: Scenario | B4: Lever | C4: Budget ceiling (EUR) | D4: affiliate spend (EUR) | E4: paid_search spend (EUR) | F4: paid_social spend (EUR) | G4: referral spend (EUR) | H4: Total spend (EUR) | I4: Customers won | J4: Net profit at recommended spend (EUR) | K4: Net profit at baseline spend (EUR) | L4: Uplift (EUR)
A5: Base case | B5: - | C5: 28603 | D5: 1558 | E5: 2687 | F5: 9515 | G5: 1298 | H5: =SUM(D5:G5) -> 15058 | I5: 470 | J5: -56843.21 | K5: -97563.64 | L5: =J5-K5 -> 40720.43
A6: Budget -20% | B6: Budget multiplier 0.8 | C6: 22882 | D6: 1558 | E6: 2687 | F6: 9515 | G6: 1298 | H6: =SUM(D6:G6) -> 15058 | I6: 470 | J6: -56843.21 | K6: -97563.64 | L6: =J6-K6 -> 40720.43
A7: Budget +20% | B7: Budget multiplier 1.2 | C7: 34323 | D7: 1558 | E7: 2687 | F7: 9515 | G7: 1298 | H7: =SUM(D7:G7) -> 15058 | I7: 470 | J7: -56843.21 | K7: -97563.64 | L7: =J7-K7 -> 40720.43
A8: Credit losses +25% | B8: Credit loss multiplier 1.25 | C8: 28603 | D8: 1558 | E8: 2687 | F8: 9515 | G8: 1032 | H8: =SUM(D8:G8) -> 14792 | I8: 460 | J8: -88647.74 | K8: -145369.99 | L8: =J8-K8 -> 56722.25
A9: Credit losses -25% | B9: Credit loss multiplier 0.75 | C9: 28603 | D9: 1558 | E9: 2687 | F9: 9515 | G9: 1298 | H9: =SUM(D9:G9) -> 15058 | I9: 470 | J9: -25020.92 | K9: -49757.3 | L9: =J9-K9 -> 24736.38
A10: Paid social curve fitted on all 24 months | B10: Summer Reach switch = 0 | C10: 28603 | D10: 1558 | E10: 2687 | F10: 9515 | G10: 1298 | H10: =SUM(D10:G10) -> 15058 | I10: 448 | J10: -55514.3 | K10: -92832.03 | L10: =J10-K10 -> 37317.73
A11: Interest after month 12 counted | B11: Interest after month 12 = measured values | C11: 28603 | D11: 1558 | E11: 2687 | F11: 9515 | G11: 1298 | H11: =SUM(D11:G11) -> 15058 | I11: 470 | J11: -32595.19 | K11: -62702.22 | L11: =J11-K11 -> 30107.03
A12: Budget fully spent (equality rule) | B12: Constraint E9 = B11 instead of <= | C12: 28603 | D12: 1558 | E12: 2687 | F12: 22564 | G12: 1298 | H12: =SUM(D12:G12) -> 28107 | I12: 572 | J12: -75920.68 | K12: -97563.64 | L12: =J12-K12 -> 21642.96
A14: Baseline spend for reference (EUR): affiliate 3,116, paid_search 5,375, paid_social 19,030, referral 1,081. Total 28,603.
A15: Reading: in every scenario with a budget ceiling, affiliate, paid search and paid social go to their lower limit. Referral goes to its upper limit, except when credit losses rise 25 percent, where it falls slightly below its baseline. Only referral earns money per customer after credit losses, and the other channels lose money on each extra customer, so the model never wants to spend more there. The last row forces the whole budget to be spent (the fixed-budget rule of the original plan); that pushes the money into paid social, the channel that wins the fewest customers per euro, which only looks better because it loses less per euro.

Sheet Pivot_Tables
A1: Pivot tables: spend, customers and cost per customer by quarter and channel
A2: Built from Data_Monthly (24 months x 4 paid channels), using its quarter column. After the data changes, right-click a pivot and choose Refresh.
A4: Ad spend (EUR)
A5: Ad spend | B5: Column Labels
A6: Row Labels | B6: affiliate | C6: paid_search | D6: paid_social | E6: referral | F6: Grand Total
A7: 2024-Q4 | B7: 3700.24 | C7: 5445.75 | D7: 8042.77 | E7: 1340.53 | F7: 18529.29
A8: 2025-Q1 | B8: 2219.08 | C8: 4812.82 | D8: 6017.4 | E8: 979.59 | F8: 14028.89
A9: 2025-Q2 | B9: 2419.52 | C9: 5129.18 | D9: 6144.29 | E9: 946.43 | F9: 14639.42
A10: 2025-Q3 | B10: 2452.11 | C10: 4997 | D10: 6065.59 | E10: 1027.57 | F10: 14542.27
A11: 2025-Q4 | B11: 4148.61 | C11: 7611.43 | D11: 11317.44 | E11: 1195.72 | F11: 24273.2
A12: 2026-Q1 | B12: 2849.87 | C12: 6257.49 | D12: 6411.41 | E12: 988.06 | F12: 16506.83
A13: 2026-Q2 | B13: 2771.68 | C13: 6052.74 | D13: 10944.37 | E13: 1159.55 | F13: 20928.34
A14: 2026-Q3 | B14: 3116.48 | C14: 5374.79 | D14: 19030.08 | E14: 1081.34 | F14: 28602.69
A15: Grand Total | B15: 23677.59 | C15: 45681.2 | D15: 73973.35 | E15: 8718.79 | F15: 152050.93
A18: Customers won
A19: Customers | B19: Column Labels
A20: Row Labels | B20: affiliate | C20: paid_search | D20: paid_social | E20: referral | F20: Grand Total
A21: 2024-Q4 | B21: 97.3 | C21: 230.52 | D21: 115.52 | E21: 111.77 | F21: 555.11
A22: 2025-Q1 | B22: 96.26 | C22: 211.82 | D22: 95.66 | E22: 116.5 | F22: 520.24
A23: 2025-Q2 | B23: 90.74 | C23: 227.65 | D23: 113.56 | E23: 98.47 | F23: 530.42
A24: 2025-Q3 | B24: 85.23 | C24: 202.23 | D24: 129.5 | E24: 104.87 | F24: 521.83
A25: 2025-Q4 | B25: 140.46 | C25: 268.7 | D25: 159.36 | E25: 109.37 | F25: 677.89
A26: 2026-Q1 | B26: 109.84 | C26: 267.16 | D26: 126.93 | E26: 100.7 | F26: 604.63
A27: 2026-Q2 | B27: 113.63 | C27: 261.97 | D27: 120.43 | E27: 111.67 | F27: 607.7
A28: 2026-Q3 | B28: 115.54 | C28: 222.13 | D28: 120.43 | E28: 109.14 | F28: 567.24
A29: Grand Total | B29: 849 | C29: 1892.18 | D29: 981.39 | E29: 862.49 | F29: 4585.06
A32: Cost per customer (EUR) = ad spend / customers
A33: Cost per customer | B33: Column Labels
A34: Row Labels | B34: affiliate | C34: paid_search | D34: paid_social | E34: referral | F34: Grand Total
A35: 2024-Q4 | B35: 38.029188 | C35: 23.623764 | D35: 69.622316 | E35: 11.993648 | F35: 33.379492
A36: 2025-Q1 | B36: 23.052982 | C36: 22.721273 | D36: 62.904035 | E36: 8.4084979 | F36: 26.966189
A37: 2025-Q2 | B37: 26.664316 | C37: 22.530991 | D37: 54.106111 | E37: 9.6113537 | F37: 27.599676
A38: 2025-Q3 | B38: 28.770503 | C38: 24.709489 | D38: 46.838533 | E38: 9.7985124 | F38: 27.867831
A39: 2025-Q4 | B39: 29.535882 | C39: 28.32687 | D39: 71.018072 | E39: 10.932797 | F39: 35.806989
A40: 2026-Q1 | B40: 25.945648 | C40: 23.422256 | D40: 50.511384 | E40: 9.8119166 | F40: 27.300713
A41: 2026-Q2 | B41: 24.39215 | C41: 23.104707 | D41: 90.877439 | E41: 10.38372 | F41: 34.438605
A42: 2026-Q3 | B42: 26.973169 | C42: 24.196597 | D42: 158.01777 | E42: 9.9078248 | F42: 50.424318
A43: Grand Total | B43: 27.888799 | C43: 24.142101 | D43: 75.376099 | E43: 10.108859 | F43: 33.162255

Sheet Notes
A1: Notes: method, data and limits
A3: Topic | B3: Note
A4: Data | B4: The Data_ sheets are pasted from the SQL views rpt.v_channel_scorecard, rpt.v_budget_inputs and rpt.v_channel_curve (extract date 2026-09-30). They are values; to refresh them, run the views again and paste.
A5: CAC | B5: (Ad spend + 2.50 EUR per identity check) / funded customers, over the whole period. Organic has no ad spend, so no CAC, ROAS or payback.
A6: LTV | B6: Observed margin per customer over the first 12 months after the first deposit: interchange + loan interest + origination fee - cost of funds - servicing. Only customers with all 12 months in the data are used.
A7: Risk-adjusted LTV | B7: LTV minus the credit loss on that customer's seasoned loans (90 percent of the principal still owed when the loan first went 90 days late). The loss covers the whole life of the loan while the LTV covers 12 months, so the comparison is conservative: interest after month 12 is not counted (about 44 to 69 EUR per customer; enter it on the Assumptions sheet to test).
A8: Response curve | B8: customers per month = a x monthly spend^b, fitted on logs with LINEST on 24 monthly points per channel. Customers are credited with the position-based attribution model, in the month of the first deposit. The fits are rough (R squared 0.14 to 0.70).
A9: Objective | B9: Net profit = customers x (risk-adjusted LTV - KYC cost per customer) - ad spend. Constraints: total spend at most the baseline budget (July to September 2026 spend), each channel between 50 and 150 percent of its baseline, referral at most 120 percent. The original plan described the budget as fixed; it is a ceiling here, because a fixed budget forces money into channels that lose money on every customer (last row of Scenarios).
A10: Not modelled | B10: Deposit margin (no balance data), retention beyond 12 months, expected loss on loans too young to judge (17 of the 1,349 loans in the cohort), and interactions between channels.
A11: Running Solver | B11: Data > Solver. The objective, changing cells and constraints are already stored. Method GRG Nonlinear. The problem is not smooth everywhere, so start from sensible values. The delivered values were found with a grid search and polished with a numerical optimizer.
A12: Credit loss caveat | B12: Per-customer losses come from the customers funded up to October 2025, whose loans have had time to default. Applying them to new customers assumes the same behaviour.
A13: Pivot tables | B13: The sheet Pivot_Tables summarises Data_Monthly by channel and quarter with three PivotTables (ad spend, customers won and a calculated field for cost per customer). They show where the cost per customer jumps: paid social from the second quarter of 2026.
A14: Lookups | B14: Sheets look up values by channel name with VLOOKUP (exact match). SUMIFS adds up the data sheets by channel and month, and COUNTIF finds the payback month.

Sheet Data_Scorecard
A1: acquisition_channel | B1: ad_spend | C1: funded_customers | D1: kyc_decisions | E1: kyc_cost | F1: cac | G1: ad_only_cac | H1: eligible_customers_12m | I1: ltv_12m | J1: revenue_12m | K1: ltv_cac | L1: roas | M1: payback_month | N1: paid_back_in_12m | O1: credit_loss_per_customer | P1: risk_adj_ltv_12m | Q1: risk_adj_ltv_cac
A2: affiliate | B2: 23677.59 | C2: 846 | D2: 1368 | E2: 3420 | F2: 32.03 | G2: 27.99 | H2: 382 | I2: 251.54 | J2: 321.21 | K2: 7.853 | L2: 11.477 | M2: 3 | N2: 1 | O2: 742.49 | P2: -490.95 | Q2: -15.328
A3: organic | B3: 0 | C3: 1401 | D3: 1831 | E3: 4577.5 | H3: 650 | I3: 167.97 | J3: 217.02 | O3: 196.21 | P3: -28.24
A4: paid_search | B4: 45681.2 | C4: 1545 | D4: 2086 | E4: 5215 | F4: 32.94 | G4: 29.57 | H4: 719 | I4: 185.36 | J4: 237.31 | K4: 5.627 | L4: 8.026 | M4: 4 | N4: 1 | O4: 217.32 | P4: -31.96 | Q4: -0.97
A5: paid_social | B5: 73973.35 | C5: 1225 | D5: 2550 | E5: 6375 | F5: 65.59 | G5: 60.39 | H5: 562 | I5: 171.28 | J5: 216.32 | K5: 2.611 | L5: 3.582 | M5: 6 | N5: 1 | O5: 225.31 | P5: -54.03 | Q5: -0.824
A6: referral | B6: 8718.79 | C6: 911 | D6: 1056 | E6: 2640 | F6: 12.47 | G6: 9.57 | H6: 467 | I6: 165.36 | J6: 217.06 | K6: 13.262 | L6: 22.68 | M6: 2 | N6: 1 | O6: 110.87 | P6: 54.49 | Q6: 4.371
A9: Source: SQL view rpt.v_channel_scorecard, extract date 2026-09-30. Values pasted from SQL; do not edit.

Sheet Data_Monthly
A1: channel_name | B1: month_start | C1: ad_spend | D1: credited_customers | E1: in_baseline_quarter | F1: ln_spend | G1: ln_customers | H1: quarter | J1: Source: SQL view rpt.v_budget_inputs. Columns A to E are pasted from SQL; F and G are formulas (natural logs, used to fit the curves) and H is a formula (the quarter, used by the pivot tables).
A2: affiliate | B2: 45566 | C2: 645.39 | D2: 18.1 | E2: 0 | F2: =LN(C2) -> 6.4698548 | G2: =LN(D2) -> 2.8959119 | H2: =YEAR(B2)&"-Q"&ROUNDUP(MONTH(B2)/3,0) -> 2024-Q4
A3: affiliate | B3: 45597 | C3: 1351.87 | D3: 36.4 | E3: 0 | F3: =LN(C3) -> 7.2092441 | G3: =LN(D3) -> 3.5945688 | H3: =YEAR(B3)&"-Q"&ROUNDUP(MONTH(B3)/3,0) -> 2024-Q4
A4: affiliate | B4: 45627 | C4: 1702.98 | D4: 42.8 | E4: 0 | F4: =LN(C4) -> 7.4401349 | G4: =LN(D4) -> 3.7565381 | H4: =YEAR(B4)&"-Q"&ROUNDUP(MONTH(B4)/3,0) -> 2024-Q4
A5: affiliate | B5: 45658 | C5: 760.88 | D5: 39.75 | E5: 0 | F5: =LN(C5) -> 6.6344757 | G5: =LN(D5) -> 3.6826098 | H5: =YEAR(B5)&"-Q"&ROUNDUP(MONTH(B5)/3,0) -> 2025-Q1
A6: affiliate | B6: 45689 | C6: 816.17 | D6: 18.38 | E6: 0 | F6: =LN(C6) -> 6.7046227 | G6: =LN(D6) -> 2.9112631 | H6: =YEAR(B6)&"-Q"&ROUNDUP(MONTH(B6)/3,0) -> 2025-Q1
A7: affiliate | B7: 45717 | C7: 642.03 | D7: 38.13 | E7: 0 | F7: =LN(C7) -> 6.464635 | G7: =LN(D7) -> 3.6410014 | H7: =YEAR(B7)&"-Q"&ROUNDUP(MONTH(B7)/3,0) -> 2025-Q1
A8: affiliate | B8: 45748 | C8: 874.68 | D8: 26.87 | E8: 0 | F8: =LN(C8) -> 6.7738581 | G8: =LN(D8) -> 3.2910104 | H8: =YEAR(B8)&"-Q"&ROUNDUP(MONTH(B8)/3,0) -> 2025-Q2
A9: affiliate | B9: 45778 | C9: 676.64 | D9: 38.77 | E9: 0 | F9: =LN(C9) -> 6.5171394 | G9: =LN(D9) -> 3.6576468 | H9: =YEAR(B9)&"-Q"&ROUNDUP(MONTH(B9)/3,0) -> 2025-Q2
A10: affiliate | B10: 45809 | C10: 868.2 | D10: 25.1 | E10: 0 | F10: =LN(C10) -> 6.7664221 | G10: =LN(D10) -> 3.2228678 | H10: =YEAR(B10)&"-Q"&ROUNDUP(MONTH(B10)/3,0) -> 2025-Q2
A11: affiliate | B11: 45839 | C11: 697.36 | D11: 21.43 | E11: 0 | F11: =LN(C11) -> 6.5473018 | G11: =LN(D11) -> 3.0647918 | H11: =YEAR(B11)&"-Q"&ROUNDUP(MONTH(B11)/3,0) -> 2025-Q3
A12: affiliate | B12: 45870 | C12: 819.03 | D12: 25.4 | E12: 0 | F12: =LN(C12) -> 6.7081207 | G12: =LN(D12) -> 3.2347492 | H12: =YEAR(B12)&"-Q"&ROUNDUP(MONTH(B12)/3,0) -> 2025-Q3
A13: affiliate | B13: 45901 | C13: 935.72 | D13: 38.4 | E13: 0 | F13: =LN(C13) -> 6.8413163 | G13: =LN(D13) -> 3.6480575 | H13: =YEAR(B13)&"-Q"&ROUNDUP(MONTH(B13)/3,0) -> 2025-Q3
... A97: referral | B97: 46266 | C97: 391.56 | D97: 39.37 | E97: 1 | F97: =LN(C97) -> 5.9701388 | G97: =LN(D97) -> 3.6730041 | H97: =YEAR(B97)&"-Q"&ROUNDUP(MONTH(B97)/3,0) -> 2026-Q3

Sheet Data_Curve
A1: acquisition_channel | B1: month_no | C1: eligible_customers | D1: avg_cum_margin | E1: avg_cum_revenue | G1: Source: SQL view rpt.v_channel_curve, pasted as values. Do not edit.
A2: affiliate | B2: 1 | C2: 799 | D2: 2.4089 | E2: 2.8089
A3: affiliate | B3: 2 | C3: 774 | D3: 17.5263 | E3: 18.4951
A4: affiliate | B4: 3 | C4: 738 | D4: 42.817 | E4: 46.164
A5: affiliate | B5: 4 | C5: 696 | D5: 65.3812 | E5: 72.9639
A6: affiliate | B6: 5 | C6: 664 | D6: 98.8193 | E6: 111.8432
A7: affiliate | B7: 6 | C7: 626 | D7: 131.4079 | E7: 151.7247
A8: affiliate | B8: 7 | C8: 594 | D8: 165.1691 | E8: 194.098
A9: affiliate | B9: 8 | C9: 562 | D9: 189.4622 | E9: 227.3822
A10: affiliate | B10: 9 | C10: 518 | D10: 208.3741 | E10: 255.3112
A11: affiliate | B11: 10 | C11: 464 | D11: 225.6014 | E11: 280.3417
A12: affiliate | B12: 11 | C12: 419 | D12: 237.5729 | E12: 299.548
A13: affiliate | B13: 12 | C13: 382 | D13: 251.5416 | E13: 321.2143
... A61: referral | B61: 12 | C61: 467 | D61: 165.3593 | E61: 217.0638
